fluxel/__init__.py
fluxel/interpreter.py
fluxel-0.3.1.dist-info/METADATA
fluxel-0.3.1.dist-info/WHEEL
fluxel-0.3.1.dist-info/entry_points.txt
fluxel-0.3.1.dist-info/top_level.txt
fluxel-0.3.1.dist-info/RECORD
