Metadata-Version: 2.1
Name: fluxel
Version: 0.3.1
Summary: A simple interpreter for Fluxel scripts
Home-page: https://github.com/gigachadtrey/fluxel/
Author: Trey
Author-email: allanleonardiii@gmail.com
Classifier: Development Status :: 3 - Alpha
Classifier: Intended Audience :: Developers
Classifier: License :: OSI Approved :: MIT License
Classifier: Operating System :: OS Independent
Classifier: Programming Language :: Python :: 3
Classifier: Programming Language :: Python :: 3.6
Classifier: Programming Language :: Python :: 3.7
Classifier: Programming Language :: Python :: 3.8
Classifier: Programming Language :: Python :: 3.9
Requires-Python: >=3.6
Requires-Dist: google-generativeai
